basemath/__init__.py
tests/__init__.py
tests/test_basemath.py
basemath-1.0.2.dist-info/LICENSE
basemath-1.0.2.dist-info/METADATA
basemath-1.0.2.dist-info/WHEEL
basemath-1.0.2.dist-info/top_level.txt
basemath-1.0.2.dist-info/RECORD
