Metadata-Version: 2.1
Name: basemath
Version: 1.0.2
Summary: A small library to work with numbers of any base
Home-page: https://github.com/m13kj/basemath
Author: eerne/m13kj (Ernest)
Author-email: infinitumco666@gmail.com
License: MIT
Platform: UNKNOWN
Classifier: Programming Language :: Python :: 3
Classifier: Natural Language :: English
Classifier: License :: OSI Approved :: MIT License
Classifier: Operating System :: OS Independent
Classifier: Intended Audience :: Science/Research
Classifier: Intended Audience :: Developers
Classifier: Topic :: Scientific/Engineering
Requires-Python: >=3.6
